rankgun/__init__.py
rankgun/main.py
rankgun/models.py
rankgun-3.0.0.dist-info/METADATA
rankgun-3.0.0.dist-info/WHEEL
rankgun-3.0.0.dist-info/RECORD
