Metadata-Version: 2.4
Name: rankgun
Version: 3.0.0
Summary: This package is a sleek simple Python wrapper for the rangkun API.
Project-URL: Homepage, https://rankgun.works/
Project-URL: Repository, https://github.com/rankgun/python
Project-URL: Documentation, https://www.rankgun.works/docs/developing/python
Author: Noah Hafner
Keywords: python
Classifier: Intended Audience :: Developers
Classifier: Programming Language :: Python
Classifier: Programming Language :: Python :: 3
Classifier: Programming Language :: Python :: 3.9
Classifier: Programming Language :: Python :: 3.10
Classifier: Programming Language :: Python :: 3.11
Classifier: Programming Language :: Python :: 3.12
Classifier: Programming Language :: Python :: 3.13
Classifier: Topic :: Software Development :: Libraries :: Python Modules
Requires-Python: <4.0,>=3.9
Requires-Dist: httpx>=0.28.1
Requires-Dist: pydantic>=2.11.4
